.DS_Store
.coveragerc
.gitignore
.pre-commit-config.yaml
CHANGELOG.md
CONTRIBUTING.md
LICENSE
README.md
pyproject.toml
setup.py
.github/.DS_Store
.github/workflows/apk.yml
.github/workflows/ci.yml
docs/configurator.md
docs/selector.md
docs/uidevice.md
docs/uiobject2.md
docs/uiwatcher.md
snippet_uiautomator/.gitignore
snippet_uiautomator/__init__.py
snippet_uiautomator/byselector.py
snippet_uiautomator/configurator.py
snippet_uiautomator/constants.py
snippet_uiautomator/errors.py
snippet_uiautomator/uiautomator.py
snippet_uiautomator/uidevice.py
snippet_uiautomator/uiobject2.py
snippet_uiautomator/uiwatcher.py
snippet_uiautomator/utils.py
snippet_uiautomator.egg-info/PKG-INFO
snippet_uiautomator.egg-info/SOURCES.txt
snippet_uiautomator.egg-info/dependency_links.txt
snippet_uiautomator.egg-info/requires.txt
snippet_uiautomator.egg-info/top_level.txt
snippet_uiautomator/android/.gitignore
snippet_uiautomator/android/build.gradle
snippet_uiautomator/android/gradle.properties
snippet_uiautomator/android/gradlew
snippet_uiautomator/android/settings.gradle
snippet_uiautomator/android/app/.gitignore
snippet_uiautomator/android/app/build.gradle
snippet_uiautomator/android/app/uiautomator.apk
snippet_uiautomator/android/app/src/main/AndroidManifest.xml
snippet_uiautomator/android/app/src/main/java/com/google/android/mobly/snippet/uiautomator/ConfiguratorSnippet.java
snippet_uiautomator/android/app/src/main/java/com/google/android/mobly/snippet/uiautomator/Converter.java
snippet_uiautomator/android/app/src/main/java/com/google/android/mobly/snippet/uiautomator/Info.java
snippet_uiautomator/android/app/src/main/java/com/google/android/mobly/snippet/uiautomator/UiAutomationSnippet.java
snippet_uiautomator/android/app/src/main/java/com/google/android/mobly/snippet/uiautomator/UiAutomator.java
snippet_uiautomator/android/app/src/main/java/com/google/android/mobly/snippet/uiautomator/UiDeviceSnippet.java
snippet_uiautomator/android/app/src/main/java/com/google/android/mobly/snippet/uiautomator/UiObject2Snippet.java
snippet_uiautomator/android/app/src/main/java/com/google/android/mobly/snippet/uiautomator/UiWatcherSnippet.java
