Metadata-Version: 2.1
Name: snippet-uiautomator
Version: 1.1.2
Summary: A Python wrapper for Android UI Automator
Home-page: https://github.com/google/snippet-uiautomator
Author: Google Inc.
Author-email: kolinlu@google.com
Maintainer-email: Kolin Lu <kolinlu@google.com>
License: 
Keywords: uiautomator
Requires-Python: >=3.7
License-File: LICENSE
